{"BSSID":"34:51:36:23:f7:71","IpAddress":"192.168.65.61","P2p0Mac":"9d:9f:38:66:83:bf","SSID":"PHICOMM_3141e2","androidId":"e29eeece86892168","batteryLevel":47,"btAddress":"e1:67:c4:63:d0:7f","btName":"Redmi Note 2","buildAbi":"armeabi-v7a","buildAbi2":"armeabi","buildBoard":"aries","buildBrand":"Xiaomi","buildCodename":"REL","buildDescription":"hermes-user 5.1.1 LMY48G 06be6188 release-keys","buildDevice":"hermes","buildFingerprint":"Xiaomi/Redmi Note 2/hermes:5.1.1/LMY48G/06be6188:user/release-keys","buildHardware":"qcom","buildHost":"SEP-68","buildId":"LMY48G","buildIncremental":"06be6188","buildManufacturer":"Xiaomi","buildModel":"Redmi Note 2","buildName":"Xiaomi","buildProduct":"hermes","buildRadioVersion":"syxknarducmx","buildRelease":"5.1.1","buildSdk":"22","buildSerialno":"b5c6acb8","buildTags":"release-keys","buildType":"user","buildUser":"buildHost","buildUtc":1462955354641,"cellScan":["33030,117835039","61723,168573983","33067,40491","33030,117546015","33580,98284165"],"ci":117546015,"contacts":["奶奶,18900396556","姑妈,13490126816","外婆,13200061587","外公,13204403993","舅舅,13001375473","舅妈,13490710580","姨父,15200651721","姨娘,13403318353","亲爱的,13490500607","老弟,13490733063","老妹,18608098447","小明,13906675597","小李子,15606590417","左奇晟,18903227356","Carl Coleman,18005982719","苗联宇,14706118985","魏铭逸,15901086917","樊然玉,15706216642","Mary Bryant,14705880797","松信怡,13302364258","王良阳,13402206526","嵇巍午,14704202737","Alicia Holmes,14701562767","龙翰珀,14703536723","李岭,13206230736","粱献甲,18704891501","Leslie Campbell,18802414909","余元豪,15108415474","伊雄陵,13802179010","经莉奇,13704620108","Thomas Gonzales,13805602256","成微儒,15608494446","陈雅,13908370655","杨炫,13303503290","Juan Ellis,18902210421","罗汉胜,13490376673","邓琴莉,15902677813","于愚,13400105871","Roberta Rivera,15107635084","祁恺佳,15205450388","姚然享,15200820206","于顺巍,18604382325","Elaine Sullivan,15501588689","于嘉,18705214943","吴铜,14702400754","禹书怡,14700094699","Gail Anderson,14707488821","杨望,18604551329","厉瑛雍,13500766285"],"cpuName":"MT6795","densityDpi":560,"deviceId":"860807120919169","deviceSvn":"26","displayId":"hermes-user 5.1.1 LMY48G 06be6188 release-keys","extraInfo":"PHICOMM_3141e2","height":0,"hidePkgs":[],"hmNotes":"","hookPkgs":[],"lac":33030,"latitude":30.5762403,"line1Number":"15708421204","longitude":104.0373671,"macAddress":"3f:0f:31:1d:92:a4","memAvailable":1249891148,"memFree":2499782296,"memTotal":3749673444,"mnc":"00","networkClass":3,"networkCountryIso":"cn","networkOperator":"46000","networkOperatorName":"中国移动","networkType":13,"networkTypeName":"LTE","phoneType":1,"rgAndroid":"23","rgAreaode":"86","rgConNames":["李由","上善若水"],"rgConsize":"2","rgCountry":"中国","rgDevice":"xiaomiRedmi 4X","rgIp":"119.4.254.138","rgLastLogin":1518364463303,"rgLocation":"四川省成都市 联通","rgNetType":"切换飞行模式","rgOrPhone":"15708421204","rgPhoneNo":"15708421204","rgServer":"飞行模式切换","rgTime":1515816327718,"rgVcode":"玉米(发码)","rgVersion":"1.6.0","rgWxEmail":"未绑定","rgWxError":"","rgWxId":"wxid_k0gkkbeiiexb22","rgWxName":"李由","rgWxNo":"未设置","rgWxPasswd":"Rmst@7890","rgWxQQ":"未绑定","rgWxStatus":"存活","rgWxWindows":"是","serialno":"b5c6acb8","simCountryIso":"cn","simOperator":"46000","simOperatorName":"中国移动","simSerialNumber":"8986003459983698456","simState":5,"subscriberId":"460008652539032","type":1,"typeName":"WIFI","width":0,"wifiScan":["TP-LINK_3154,4c:1f:cc:30:2d:f2,[WPA2-PSK-CCMP][ESS],-84,2437,534884326","MERCURY_baed9d,54:89:98:6c:37:75,[WPA-PSK-CCMP][WPA2-PSK-CCMP][WPS][ESS],-64,2462,206327888","Netcore_597437,f4:ec:38:38:44:24,[WPA2-PSK-CCMP][WPS][ESS],-66,2462,1768626685","TP-LINK_c8cbfe,d8:15:0d:01:c4:f0,[WPA2-PSK-CCMP][WPS][ESS],-51,2437,2501127173","PHICOMM_1e1053,80:89:17:e8:da:48,[WPA2-PSK-CCMP][WPS][ESS],-77,2437,210833430"]}