{"BSSID":"5b:11:d3:5c:cb:90","IpAddress":"192.168.3.95","P2p0Mac":"77:ec:08:37:0b:00","SSID":"Netcore_699dc0","androidId":"bc8bd3ff0860098c","batteryLevel":70,"btAddress":"67:ea:19:1c:da:c7","btName":"Redmi 4","buildAbi":"armeabi-v7a","buildAbi2":"armeabi","buildBoard":"roth","buildBrand":"Xiaomi","buildCodename":"REL","buildDescription":"Redmi 4-user 5.0 LRX21M aecbf132 release-keys","buildDevice":"Redmi 4","buildFingerprint":"Xiaomi/Redmi 4/Redmi 4:5.0/LRX21M/aecbf132:user/release-keys","buildHardware":"qcom","buildHost":"LGEACI2R5","buildId":"LRX21M","buildIncremental":"aecbf132","buildManufacturer":"Xiaomi","buildModel":"Redmi 4","buildName":"Xiaomi","buildProduct":"Redmi 4","buildRadioVersion":"xgdeoqhfwwuezvo","buildRelease":"5.0","buildSdk":"21","buildSerialno":"86042dfe","buildTags":"release-keys","buildType":"user","buildUser":"lgmobile","buildUtc":1457601727172,"cellScan":["33293,139840003","33037,118129185","61720,168410567","61720,169382996","61705,169370187"],"ci":168410567,"contacts":["奶奶,13490640510","姑妈,15601712730","外婆,13105848077","外公,18902764800","舅舅,15504013267","舅妈,15207516055","姨父,13303191850","姨娘,15202884552","亲爱的,15904462324","老弟,15304926891","老妹,15704304073","小明,18900662258","小李子,15705440045","吴校,15303810200","Paula Olson,18007517309","任图仙,13602100198","陈礼,14708065813","汪魄幸,15503180004","Charles Matthews,15508737270","邱熙况,13803730540","元岭江,13801926098","项秋贤,18607736385","Brent Morgan,13104288901","李秋,13806867135","吴贵,13490203421","长孙思海,13490563481","Clyde Marshall,13490561267","杨宫,13490182850","陈生任,13402768386","蓝微渠,18802442126","Don Ray,14701701732","于薇,13602000700","钮吉龙,14700647322","杨三津,13103623069","Joseph Wagner,15607001321","杜宣晟,13208341543","殷嘉彦,15807342836","宗享业,15504158300","Benjamin Berry,13002917827","栾硕璐,15108478202","张友彤,14705187457","李佳随,13704181005","Stephanie Lewis,13607041959"],"cpuName":"Qualcomm Technologies, Inc MSM8953","densityDpi":320,"deviceId":"860594143861814","deviceSvn":"49","displayId":"Redmi 4-user 5.0 LRX21M aecbf132 release-keys","extraInfo":"Netcore_699dc0","height":0,"hidePkgs":[],"hmNotes":"","hookPkgs":[],"lac":61720,"latitude":30.8949715,"line1Number":"13438451096","longitude":103.7332956,"macAddress":"0c:8a:01:cf:7f:f8","memAvailable":23598371,"memFree":70795115,"memTotal":94393486,"mnc":"00","networkClass":2,"networkCountryIso":"cn","networkOperator":"46002","networkOperatorName":"中国移动","networkType":17,"networkTypeName":"TD_SCDMA","phoneType":1,"rgAndroid":"23","rgAreaode":"86","rgConNames":["上善若水","于靖游"],"rgConsize":"2","rgCountry":"中国","rgDevice":"xiaomiRedmi 4X","rgIp":"101.206.166.122","rgLastLogin":1518352584759,"rgLocation":"四川省 联通","rgNetType":"切换飞行模式","rgOrPhone":"13438451096","rgPhoneNo":"13438451096","rgServer":"飞行模式切换","rgTime":1515314360347,"rgVcode":"玉米(发码)","rgVersion":"1.6.0","rgWxEmail":"未绑定","rgWxError":"","rgWxId":"wxid_ph320x8b3alc22","rgWxName":"于靖游","rgWxNo":"未设置","rgWxPasswd":"Rmst@7890","rgWxQQ":"未绑定","rgWxStatus":"存活","rgWxWindows":"是","serialno":"86042dfe","simCountryIso":"cn","simOperator":"46002","simOperatorName":"中国移动","simSerialNumber":"8986006317975174895","simState":5,"subscriberId":"460026600251477","type":1,"typeName":"WIFI","width":0,"wifiScan":["Tenda_9caec1,1c:60:de:64:13:ee,[WPA-PSK-CCMP][WPA2-PSK-CCMP][WPS][ESS],-85,2412,2107738459","FAST_87b854,50:bd:5f:22:b8:46,[WPA2-PSK-CCMP][WPS][ESS],-89,2437,1364233575","TP-LINK_c0fcbe,64:5d:92:4e:51:a9,[WPA2-PSK-CCMP][WPS][ESS],-76,2417,218093799","TP-LINK_ec1fcb,0c:96:bf:7d:87:3c,[WPA2-PSK-CCMP][ESS],-83,2437,2589029581","FAST_416420,14:75:90:55:8f:62,[WPA2-PSK-CCMP][ESS],-71,2412,215281836"]}