{"BSSID":"84:4f:2e:29:75:50","IpAddress":"192.168.8.237","P2p0Mac":"68:4d:8c:33:3d:c6","SSID":"MERCURY_032658","androidId":"ae48ae1195d053f2","batteryLevel":74,"btAddress":"31:bf:54:a7:0d:29","btName":"samsung SM-N9300","buildAbi":"armeabi-v7a","buildAbi2":"armeabi","buildBoard":"cardhu","buildBrand":"samsung","buildCodename":"REL","buildDescription":"samsung SM-N9300-user 6.0.1 MMB29T af753a57 release-keys","buildDevice":"samsung SM-N9300","buildFingerprint":"samsung/samsung SM-N9300/samsung SM-N9300:6.0.1/MMB29T/af753a57:user/release-keys","buildHardware":"qcom","buildHost":"bs213","buildId":"MMB29T","buildIncremental":"af753a57","buildManufacturer":"samsung","buildModel":"samsung SM-N9300","buildName":"samsung","buildProduct":"samsung SM-N9300","buildRadioVersion":"sjuocifnu","buildRelease":"6.0.1","buildSdk":"23","buildSerialno":"fa231861","buildTags":"release-keys","buildType":"user","buildUser":"buildHost","buildUtc":1474895095863,"cellScan":["33028,33184","61702,169507027","33292,98228352","33292,96715137","33292,98238592"],"ci":96715137,"contacts":["奶奶,15200084551","姑妈,13490761048","外婆,18607198961","外公,13306941288","舅舅,13604100002","舅妈,13490220560","姨父,18800453172","姨娘,13205612457","亲爱的,18902828389","老弟,18805798683","老妹,13490162663","小明,18908578670","小李子,18706655582","陶魁逵,15701947997","James Gonzales,14704377459","杨异霖,15800827434","杨炎,15301800369","王昱,14702428217","Jason Coleman,18801838062","薛璎立,15705662824","康精佑,13490139539","荀韶威,15306368065","Marcus Simpson,15300687391","靳红禄,15607847540","李韶影,15802256135","乐屏雪,15005940068","Terry Watkins,15203125481","陈裕利,13307330500","芮启可,15001938251","张盛,13505358447","Jay Franklin,13806071994","杨炫午,13205290339","汲阳思,13490603626","王为律,13307836092","Marion Woods,15300542614","陆皓室,13490728428","杨剑,18602014934","李新,15600926466","Beatrice Powell,18605400581","柳宇欣,15908515419","余妙思,18707557283","吴殊,13701987249","Rosa Grant,13703102815"],"cpuName":"Qualcomm Technologies, Inc MSM8996","densityDpi":480,"deviceId":"862246353165497","deviceSvn":"55","displayId":"samsung SM-N9300-user 6.0.1 MMB29T af753a57 release-keys","extraInfo":"MERCURY_032658","height":0,"hidePkgs":[],"hmNotes":"","hookPkgs":[],"lac":33292,"latitude":30.5494744,"line1Number":"15302998848","longitude":103.9378029,"macAddress":"96:09:67:82:ae:15","memAvailable":611005799,"memFree":1222011599,"memTotal":1833017398,"mnc":"03","networkClass":3,"networkCountryIso":"cn","networkOperator":"46003","networkOperatorName":"中国电信","networkType":13,"networkTypeName":"LTE","phoneType":2,"rgAndroid":"23","rgAreaode":"86","rgConNames":["上善若水","仰游涂"],"rgConsize":"2","rgCountry":"中国","rgDevice":"xiaomiRedmi 4X","rgIp":"119.4.252.212","rgLastLogin":1518374501027,"rgLocation":"四川省成都市 联通","rgNetType":"切换飞行模式","rgOrPhone":"15302998848","rgPhoneNo":"15302998848","rgServer":"飞行模式切换","rgTime":1516101799596,"rgVcode":"尚一品(发码)","rgVersion":"1.6.3","rgWxEmail":"未绑定","rgWxError":"","rgWxId":"wxid_cbaa5nrx5hta22","rgWxName":"仰游涂","rgWxNo":"未设置","rgWxPasswd":"Rmst@7890","rgWxQQ":"未绑定","rgWxStatus":"存活","rgWxWindows":"否","serialno":"fa231861","simCountryIso":"cn","simOperator":"46003","simOperatorName":"中国电信","simSerialNumber":"8986114072845265729","simState":5,"subscriberId":"460035729832150","type":1,"typeName":"WIFI","width":0,"wifiScan":["Netcore_e0e165,64:3a:b1:40:e0:e2,[WPA-PSK-CCMP][WPA2-PSK-CCMP][ESS],-91,2462,259547687","TP-LINK_dc38,2c:95:7f:2c:3b:a3,[WPA2-PSK-CCMP][ESS],-71,2412,415794853","PHICOMM_dc0f31,ec:26:ca:08:57:16,[WPA-PSK-CCMP][WPA2-PSK-CCMP][ESS],-78,2412,384713777","Netcore_9ec1f3,24:69:68:8b:78:ef,[WPA-PSK-CCMP][WPA2-PSK-CCMP][WPS][ESS],-76,2472,286429199","Tenda_591f42,20:dc:e6:d7:e1:42,[WPA-PSK-CCMP][WPA2-PSK-CCMP][ESS],-84,2442,225367582"]}