{"BSSID":"56:c9:78:b8:57:ee","IpAddress":"192.168.26.171","P2p0Mac":"38:3f:d5:24:57:da","SSID":"TP-LINK_053cae","androidId":"f5fb52b9ccd3320d","batteryLevel":55,"btAddress":"9e:93:d1:ad:72:c0","btName":"2014501","buildAbi":"armeabi-v7a","buildAbi2":"armeabi","buildBoard":"p760","buildBrand":"Xiaomi","buildCodename":"REL","buildDescription":"2014501-user 7.1.2 NMF26Q cd651727 release-keys","buildDevice":"HM2014501","buildFingerprint":"Xiaomi/2014501/HM2014501:7.1.2/NMF26Q/cd651727:user/release-keys","buildHardware":"qcom","buildHost":"huangshan","buildId":"NMF26Q","buildIncremental":"cd651727","buildManufacturer":"Xiaomi","buildModel":"2014501","buildName":"Xiaomi","buildProduct":"2014501","buildRadioVersion":"agppvzqgtf","buildRelease":"7.1.2","buildSdk":"25","buildSerialno":"b72d6f3a","buildTags":"release-keys","buildType":"user","buildUser":"lgmobile","buildUtc":1504822778707,"cellScan":["39938,163708721","33049,118165281","33061,97360768","61713,168916584","61731,30312"],"ci":168916584,"contacts":["奶奶,13906127997","姑妈,13800796602","外婆,15801944235","外公,13202238571","舅舅,18800884831","舅妈,13602749027","姨父,18907043530","姨娘,13808737813","亲爱的,18605781936","老弟,13700940671","老妹,18005916266","小明,18807070995","小李子,18803117365","王随,15702462247","Cindy Russell,18804393301","储如孝,13807877489","柯添佩,13902601690","松王妙,15605837683","Holly Gardner,13200987764","宣京相,13108305732","单让翔,18007343151","陈伊善,15500186040","Rhonda Matthews,15607411807","王静,13306168731","邹宽鹏,18705126850","祝彤童,18905978493","Katie Lee,18904663605","杨瑞密,15100707309","王生宏,18804916138","金会乐,13303812123","Benjamin Fisher,18003795182","靳和旭,15806874875","卜书珊,15308313721","张实烈,15902391097","Virginia Cole,13402188298","乐麟谦,18701107700","吕西建,13006203261","王奇仕,13308166870","Donna Moore,13490681862","暴仕嘉,15808238531","李余土,18907045778"],"cpuName":"MT6582","densityDpi":320,"deviceId":"860708857983529","deviceSvn":"46","displayId":"2014501-user 7.1.2 NMF26Q cd651727 release-keys","extraInfo":"TP-LINK_053cae","height":0,"hidePkgs":[],"hmNotes":"","hookPkgs":[],"lac":61713,"latitude":30.830165,"line1Number":"18781932840","longitude":104.301145,"macAddress":"7f:a1:8a:27:5a:12","memAvailable":31422045,"memFree":62844091,"memTotal":94266136,"mnc":"00","networkClass":1,"networkCountryIso":"cn","networkOperator":"46002","networkOperatorName":"中国移动","networkType":2,"networkTypeName":"EDGE","phoneType":1,"rgAndroid":"23","rgAreaode":"86","rgConNames":["李设然","上善若水"],"rgConsize":"2","rgCountry":"中国","rgDevice":"xiaomiRedmi 4X","rgIp":"101.206.167.90","rgLastLogin":1518365818782,"rgLocation":"四川省 联通","rgNetType":"切换飞行模式","rgOrPhone":"18781932840","rgPhoneNo":"18781932840","rgServer":"飞行模式切换","rgTime":1516001453691,"rgVcode":"玉米(发码)","rgVersion":"1.6.3","rgWxEmail":"未绑定","rgWxError":"","rgWxId":"wxid_z40i2nnpu3ju22","rgWxName":"李设然","rgWxNo":"未设置","rgWxPasswd":"Rmst@7890","rgWxQQ":"未绑定","rgWxStatus":"存活","rgWxWindows":"是","serialno":"b72d6f3a","simCountryIso":"cn","simOperator":"46002","simOperatorName":"中国移动","simSerialNumber":"8986008294976379366","simState":5,"subscriberId":"460025179665182","type":1,"typeName":"WIFI","width":0,"wifiScan":["PHICOMM_bfd1dd,64:3a:b1:d4:1e:d2,[WPA-PSK-CCMP][WPA2-PSK-CCMP][WPS][ESS],-94,2437,3294738418","PHICOMM_149742,a8:15:4d:2c:c5:72,[WPA2-PSK-CCMP][WPS][ESS],-76,2472,1926334165","Tenda_5a9497,9c:d2:4b:4a:fb:6c,[WPA2-PSK-CCMP][WPS][ESS],-85,2462,378083719","Tenda_697cbf,14:75:90:bc:0b:a0,[WPA-PSK-CCMP][WPA2-PSK-CCMP][WPS][ESS],-91,2462,208115978","Tenda_dc386b,f4:dc:f9:b9:f6:a4,[WPA-PSK-CCMP][WPA2-PSK-CCMP][WPS][ESS],-91,2432,450643495"]}