{"BSSID":"71:b4:b9:6b:a0:c9","IpAddress":"192.168.41.194","P2p0Mac":"84:f0:e6:b2:1f:a7","SSID":"Netcore_37fd21","androidId":"405605ba5ba472f3","batteryLevel":47,"btAddress":"7c:ad:73:35:8b:71","btName":"HM NOTE 1TD","buildAbi":"armeabi-v7a","buildAbi2":"armeabi","buildBoard":"ether","buildBrand":"Xiaomi","buildCodename":"REL","buildDescription":"lcsh92_wet_tdd-user 6.0.1 MMB29T dad0bbf3 release-keys","buildDevice":"lcsh92_wet_tdd","buildFingerprint":"Xiaomi/HM NOTE 1TD/lcsh92_wet_tdd:6.0.1/MMB29T/dad0bbf3:user/release-keys","buildHardware":"qcom","buildHost":"huawei-server-05","buildId":"MMB29T","buildIncremental":"dad0bbf3","buildManufacturer":"Xiaomi","buildModel":"HM NOTE 1TD","buildName":"Xiaomi","buildProduct":"lcsh92_wet_tdd","buildRadioVersion":"qcbsfnqez","buildRelease":"6.0.1","buildSdk":"23","buildSerialno":"6589baf9","buildTags":"release-keys","buildType":"user","buildUser":"builder","buildUtc":1455693987058,"cellScan":["61722,169492592","32905,6191","32905,21176","32905,58771","33028,33721"],"ci":6191,"contacts":["奶奶,15008300364","姑妈,13106488594","外婆,15303257712","外公,13504772965","舅舅,13508325831","舅妈,13707701676","姨父,15003197325","姨娘,15604910788","亲爱的,13490191044","老弟,15201158084","老妹,13803567567","小明,13103596222","小李子,18002532946","王郁三,15701282964","Vincent Green,15701287642","祖经轩,13908514581","李全,15002962078","杨素,13302610125","Ricky Carter,13300117239","许君绵,15604664924","杨豪翰,18600094839","王隆艺,18908198096","Alexander Gardner,18007882827","杨伊克,15805970828","夏侯杭梁,15502666599","吴思贺,13904948535","Kenneth Black,13606244130","韦松顺,15708808941","羊界青,13703605485","庞效嘉,13008567555","Lillian Stephens,13001007920","卫新,13407530145","舒扬泉,13501355511","杨勇,15108358821","Daniel Edwards,15205206415","李观勋,13604021779","段松颖,13508510304","吴望,13701398980","Thelma Sims,13606037644","吴绣,15601570825"],"cpuName":"MT6592","densityDpi":480,"deviceId":"866076788321019","deviceSvn":"55","displayId":"lcsh92_wet_tdd-user 6.0.1 MMB29T dad0bbf3 release-keys","extraInfo":"Netcore_37fd21","height":0,"hidePkgs":[],"hmNotes":"","hookPkgs":[],"lac":32905,"latitude":30.543612,"line1Number":"18149735143","longitude":104.0194151,"macAddress":"7c:db:3b:d6:1b:b8","memAvailable":1250178767,"memFree":2500357534,"memTotal":3750536301,"mnc":"03","networkClass":2,"networkCountryIso":"cn","networkOperator":"46003","networkOperatorName":"中国电信","networkType":5,"networkTypeName":"CDMA - EvDo rev. 0","phoneType":2,"rgAndroid":"23","rgAreaode":"86","rgConNames":["嵇湘茂","上善若水"],"rgConsize":"2","rgCountry":"中国","rgDevice":"xiaomiRedmi 4X","rgIp":"119.4.253.215","rgLastLogin":1518365028413,"rgLocation":"四川省成都市 联通","rgNetType":"切换飞行模式","rgOrPhone":"18149735143","rgPhoneNo":"18149735143","rgServer":"飞行模式切换","rgTime":1515228437687,"rgVcode":"尚一品(发码)","rgVersion":"1.6.0","rgWxEmail":"未绑定","rgWxError":"","rgWxId":"wxid_oo2rzgbsfgp22","rgWxName":"嵇湘茂","rgWxNo":"未设置","rgWxPasswd":"Rmst@7890","rgWxQQ":"未绑定","rgWxStatus":"存活","rgWxWindows":"是","serialno":"6589baf9","simCountryIso":"cn","simOperator":"46003","simOperatorName":"中国电信","simSerialNumber":"8986062212657709383","simState":5,"subscriberId":"460037526143141","type":1,"typeName":"WIFI","width":0,"wifiScan":["ChainaNet_f103,24:05:0f:65:52:73,[WPA2-PSK-CCMP][WPS][ESS],-58,2472,472330762","Tenda_0386ba,64:3a:b1:79:2b:da,[WPA-PSK-CCMP][WPA2-PSK-CCMP][WPS][ESS],-57,2437,272114675","Tenda_caed04,1c:fa:68:ab:75:5a,[WPA2-PSK-CCMP][WPS][ESS],-81,2462,1609126992","Netcore_be3053,ec:38:8f:8d:24:f8,[WPA-PSK-CCMP][WPA2-PSK-CCMP][WPS][ESS],-79,2437,451074912","Netcore_f31642,ec:26:ca:5c:b4:ba,[WPA-PSK-CCMP][WPA2-PSK-CCMP][ESS],-55,2412,572728400"]}