{"BSSID":"9a:57:ca:79:49:08","IpAddress":"10.10.34.17","P2p0Mac":"52:de:75:13:b3:0c","SSID":"MERCURY_4266a8","androidId":"33b88e5a05d7e907","batteryLevel":47,"btAddress":"1c:4d:38:4b:9b:04","btName":"OPPO A33m","buildAbi":"armeabi-v7a","buildAbi2":"armeabi","buildBoard":"su640","buildBrand":"OPPO","buildCodename":"REL","buildDescription":"OPPO A33m-user 7.0.0 NRD90M 8e9d8a29 release-keys","buildDevice":"OPPO A33m","buildFingerprint":"OPPO/OPPO A33m/OPPO A33m:7.0.0/NRD90M/8e9d8a29:user/release-keys","buildHardware":"qcom","buildHost":"qh-miui-ota-bd54","buildId":"NRD90M","buildIncremental":"8e9d8a29","buildManufacturer":"OPPO","buildModel":"OPPO A33m","buildName":"OPPO","buildProduct":"OPPO A33m","buildRadioVersion":"hijsnykfuflok","buildRelease":"7.0.0","buildSdk":"24","buildSerialno":"f6aa843e","buildTags":"release-keys","buildType":"user","buildUser":"android","buildUtc":1483886663451,"cellScan":["33061,43342","33296,98493825","61701,167988020","61699,168117712","61703,168117712"],"ci":167988020,"contacts":["奶奶,13908571866","姑妈,13704298665","外婆,15303508698","外公,13608557468","舅舅,14705460819","舅妈,18803047576","姨父,13107310644","姨娘,13206656058","亲爱的,13505944426","老弟,15002623796","老妹,13503988697","小明,13706110005","小李子,13501984897","伊桐夜,13607347990","Arthur Anderson,13704654635","李易,13490562574","颜实界,15907292303","汲阁豪,13708796611","Mike Daniels,13806098046","乐添演,13601952363","于易,15603495071","余彦启,13490361375","Tommy Tucker,13490210148","姜惠鹄,18001611481","李宣,15907137386","张烈,13905545736","Tony Griffin,13603781266","李璇嘉,14705414285","任海耕,15901266108","施书童,13904710831","Megan Peterson,13501228746","李鹄茂,15507901615","张贤石,13490281286","潘坚贤,15702042012","Anna Elliott,15700445878","张军,13705431747","王权,13502855558","王怡,15001875810","Marcus Lewis,15902042541","李念迅,18603320997","戎梦声,15006069056","陈立节,15200066005","Bonnie Weaver,15104082585"],"cpuName":"Qualcomm Technologies, Inc MSM8916","densityDpi":240,"deviceId":"863477874311992","deviceSvn":"32","displayId":"OPPO A33m-user 7.0.0 NRD90M 8e9d8a29 release-keys","extraInfo":"uninet","height":0,"hidePkgs":[],"hmNotes":"","hookPkgs":[],"lac":61701,"latitude":30.7245244,"line1Number":"18930537546","longitude":104.2122181,"macAddress":"2c:f5:e8:95:b5:cf","memAvailable":5479466512,"memFree":10958933025,"memTotal":16438399537,"mnc":"03","networkClass":2,"networkCountryIso":"cn","networkOperator":"46003","networkOperatorName":"中国电信","networkType":5,"networkTypeName":"CDMA - EvDo rev. 0","phoneType":2,"rgAndroid":"23","rgAreaode":"86","rgConNames":["上善若水","吴同"],"rgConsize":"2","rgCountry":"中国","rgDevice":"xiaomiRedmi 4X","rgIp":"119.4.252.21","rgLastLogin":1518351220050,"rgLocation":"四川省成都市 联通","rgNetType":"切换飞行模式","rgOrPhone":"18930537546","rgPhoneNo":"18930537546","rgServer":"飞行模式切换","rgTime":1515134507371,"rgVcode":"尚一品(发码)","rgVersion":"1.6.0","rgWxEmail":"未绑定","rgWxError":"","rgWxId":"wxid_3ha91ehcbsms22","rgWxName":"吴同","rgWxNo":"未设置","rgWxPasswd":"Rmst@7890","rgWxQQ":"未绑定","rgWxStatus":"存活","rgWxWindows":"否","serialno":"f6aa843e","simCountryIso":"cn","simOperator":"46003","simOperatorName":"中国电信","simSerialNumber":"8986116548902417578","simState":5,"subscriberId":"460033986978750","type":0,"typeName":"MOBILE","width":0,"wifiScan":["Netcore_5fbadc,00:23:c9:b0:50:fa,[WPA-PSK-CCMP][WPA2-PSK-CCMP][WPS][ESS],-75,2412,3502435024","Netcore_510538,00:23:c9:99:b4:0d,[WPA2-PSK-CCMP][WPS][ESS],-81,2437,223680397","MERCURY_7498cf,bc:46:99:01:1b:88,[WPA2-PSK-CCMP][WPS][ESS],-73,2412,2628334799","MERCURY_2fcb,08:10:79:8b:57:96,[WPA-PSK-CCMP][WPA2-PSK-CCMP][WPS][ESS],-93,2412,3716435953","FAST_0416,58:2a:f7:86:b2:f5,[WPA2-PSK-CCMP][WPS][ESS],-51,2437,1037035506"]}