{"BSSID":"1e:b1:ff:60:8d:55","IpAddress":"10.58.46.137","P2p0Mac":"f5:82:3c:63:4c:c8","SSID":"PHICOMM_e154fe","androidId":"89f9df82a5d85b5f","batteryLevel":66,"btAddress":"4c:16:c5:19:ca:11","btName":"ZTE G718C","buildAbi":"armeabi-v7a","buildAbi2":"armeabi","buildBoard":"MSM8916","buildBrand":"ZTE","buildCodename":"REL","buildDescription":"ZTE-G718C-user 5.0 LRX21M ca5eb21c release-keys","buildDevice":"ZTE-G718C","buildFingerprint":"ZTE/ZTE G718C/ZTE-G718C:5.0/LRX21M/ca5eb21c:user/release-keys","buildHardware":"qcom","buildHost":"wcc-miui-ota-bd07.bj","buildId":"LRX21M","buildIncremental":"ca5eb21c","buildManufacturer":"ZTE","buildModel":"ZTE G718C","buildName":"ZTE","buildProduct":"ZTE-G718C","buildRadioVersion":"qemhuohwjvdmhhwe","buildRelease":"5.0","buildSdk":"21","buildSerialno":"b3acccc8","buildTags":"release-keys","buildType":"user","buildUser":"Server","buildUtc":1497613712520,"cellScan":["33038,118247968","33301,139646209","33038,118595359","61729,169973414","61729,168846807"],"ci":118595359,"contacts":["奶奶,13405973331","姑妈,13904395433","外婆,15807838315","外公,13104492270","舅舅,13704670826","舅妈,15901434354","姨父,13605107508","姨娘,13601676410","亲爱的,13490868209","老弟,13902310823","老妹,18001761542","小明,15100317536","小李子,13501918425","霍梧信,18808181904","Sara Woods,18807038928","韦夜石,18806785933","于畏学,13304403817","杨观,15701062737","George Cooper,14708221037","江蔚任,18705677552","阮荃桂,13900687697","俞贵书,13604790930","Regina Wright,13607063201","王奇,15604245601","吴硕,15004918378","宁厚宏,15908616107","Tyler Baker,15805900733","吴同,13490837137","费建善,13607170709","张靖,14708824400","Sue Perkins,14704074268","王相,18003762538","王胜凇,18807923452","王兴,13808771454","Judith Duncan,13801515000","王郁,13904211938","吴吾,15803058947","李朔印,15104617723","Virginia Lawson,15104718100","王和贵,13705440622","惠添青,18905589033"],"cpuName":"Qualcomm MSM8926","densityDpi":320,"deviceId":"860219572164361","deviceSvn":"40","displayId":"ZTE-G718C-user 5.0 LRX21M ca5eb21c release-keys","extraInfo":"3gnet","height":0,"hidePkgs":[],"hmNotes":"","hookPkgs":[],"lac":33038,"latitude":30.6947482,"line1Number":"13540184432","longitude":103.7630725,"macAddress":"bd:c3:3f:02:fb:0b","memAvailable":51215894,"memFree":153647683,"memTotal":204863577,"mnc":"00","networkClass":1,"networkCountryIso":"cn","networkOperator":"46000","networkOperatorName":"中国移动","networkType":2,"networkTypeName":"EDGE","phoneType":1,"rgAndroid":"23","rgAreaode":"86","rgConNames":["上善若水","王任倩"],"rgConsize":"2","rgCountry":"中国","rgDevice":"xiaomiRedmi 4X","rgIp":"171.210.169.14","rgLastLogin":1518396994326,"rgLocation":"四川省成都市 电信","rgNetType":"切换飞行模式","rgOrPhone":"13540184432","rgPhoneNo":"13540184432","rgServer":"飞行模式切换","rgTime":1516001995861,"rgVcode":"玉米(发码)","rgVersion":"1.6.3","rgWxEmail":"未绑定","rgWxError":"","rgWxId":"wxid_quw6y4f1kskw22","rgWxName":"王任倩","rgWxNo":"未设置","rgWxPasswd":"Rmst@7890","rgWxQQ":"未绑定","rgWxStatus":"存活","rgWxWindows":"否","serialno":"b3acccc8","simCountryIso":"cn","simOperator":"46000","simOperatorName":"中国移动","simSerialNumber":"8986028757116272100","simState":5,"subscriberId":"460008337630889","type":0,"typeName":"MOBILE","width":0,"wifiScan":["Tenda_173375,6c:59:40:ff:bf:c7,[WPA-PSK-CCMP][WPA2-PSK-CCMP][ESS],-59,2412,983534315","iTV-2d11,64:3a:b1:79:53:8a,[WPA2-PSK-CCMP][ESS],-71,2417,880131598","TP-LINK_276a,d0:c7:c0:84:0f:aa,[WPA2-PSK-CCMP][ESS],-56,2472,192776062","FAST_88caa6,80:89:17:c7:24:f4,[WPA2-PSK-CCMP][WPS][ESS],-89,2412,3418536346","TP-LINK_3266,c0:61:18:91:58:18,[WPA2-PSK-CCMP][WPS][ESS],-87,2462,471050255"]}