{"BSSID":"25:0b:0c:12:dd:06","IpAddress":"192.168.67.239","P2p0Mac":"17:e5:19:8e:67:47","SSID":"Tenda_b85a8c","androidId":"ca44b11ca64d3796","batteryLevel":46,"btAddress":"45:0f:37:7f:22:f7","btName":"M5 Note","buildAbi":"armeabi-v7a","buildAbi2":"armeabi","buildBoard":"hummingbird","buildBrand":"Meizu","buildCodename":"REL","buildDescription":"meizu_M5 Note-user 7.1.2 NMF26Q 701cbd60 release-keys","buildDevice":"M5Note","buildFingerprint":"Meizu/M5 Note/M5Note:7.1.2/NMF26Q/701cbd60:user/release-keys","buildHardware":"qcom","buildHost":"huawei-server-05","buildId":"NMF26Q","buildIncremental":"701cbd60","buildManufacturer":"Meizu","buildModel":"M5 Note","buildName":"Meizu","buildProduct":"meizu_M5 Note","buildRadioVersion":"rqeqburrzymetk","buildRelease":"7.1.2","buildSdk":"25","buildSerialno":"6646dcfc","buildTags":"release-keys","buildType":"user","buildUser":"jenkins","buildUtc":1489341203875,"cellScan":["32813,134673413","32813,99869312","32819,10034","61726,32236","32819,11171"],"ci":32236,"contacts":["奶奶,13490344001","姑妈,13302395191","外婆,15208053964","外公,13905096040","舅舅,18903765103","舅妈,18606685673","姨父,15705875685","姨娘,13602006546","亲爱的,15307650850","老弟,13490812353","老妹,15201415653","小明,13400956076","小李子,13408191462","裘平薇,13601814162","Shane Watkins,13605516849","洪玉升,18807078205","黄善平,13600496097","华罗伊,13490767004","Mike Rodriguez,18006166731","杨奇,18704105877","余联,18002415405","杨兴仙,18002222730","Roy Ferguson,18906251111","栾默由,18005248989","杨尚保,13101615975","杨稼,13490472831","Janice Duncan,13302925362","顾先虹,13704005842","于望世,15706235149","董甲竞,18807600329","Jeanne Fox,18700191412","杨心,13107930446","贲楷桂,15001684123","唐旺桐,14708678860","Vernon Gomez,15708372769","万萱界,18004514778","陈勇殊,18002186340","王涂梁,18702951844","Aaron Hicks,18805996278","杨翔阳,13608713766","杨演,18802933591"],"cpuName":"MT6755M","densityDpi":240,"deviceId":"860767311969540","deviceSvn":"88","displayId":"meizu_M5 Note-user 7.1.2 NMF26Q 701cbd60 release-keys","extraInfo":"Tenda_b85a8c","height":0,"hidePkgs":[],"hmNotes":"","hookPkgs":[],"lac":61726,"latitude":30.5496624,"line1Number":"18224499385","longitude":104.2219247,"macAddress":"aa:b7:ed:93:ac:70","memAvailable":5479621935,"memFree":10959243872,"memTotal":16438865807,"mnc":"00","networkClass":2,"networkCountryIso":"cn","networkOperator":"46000","networkOperatorName":"中国移动","networkType":8,"networkTypeName":"HSDPA","phoneType":1,"rgAndroid":"23","rgAreaode":"86","rgConNames":["计倩若","上善若水"],"rgConsize":"2","rgCountry":"中国","rgDevice":"xiaomiRedmi 4X","rgIp":"119.4.253.22","rgLastLogin":1518349379186,"rgLocation":"四川省成都市 联通","rgNetType":"切换飞行模式","rgOrPhone":"18224499385","rgPhoneNo":"18224499385","rgServer":"飞行模式切换","rgTime":1514969358276,"rgVcode":"玉米(发码)","rgVersion":"1.6.0","rgWxEmail":"未绑定","rgWxError":"","rgWxId":"wxid_mb5uat6bdjrl22","rgWxName":"计倩若","rgWxNo":"未设置","rgWxPasswd":"Rmst@7890","rgWxQQ":"未绑定","rgWxStatus":"存活","rgWxWindows":"是","serialno":"6646dcfc","simCountryIso":"cn","simOperator":"46000","simOperatorName":"中国移动","simSerialNumber":"8986022024432608914","simState":5,"subscriberId":"460005698840615","type":1,"typeName":"WIFI","width":0,"wifiScan":["iTV-2527,fc:d7:33:18:f1:c8,[WPA2-PSK-CCMP][WPS][ESS],-56,2412,209505553","Netcore_eb4165,24:05:0f:29:16:21,[WPA2-PSK-CCMP][ESS],-65,2412,1128537422","Netcore_276105,e0:4f:bd:f5:e8:42,[WPA-PSK-CCMP][WPA2-PSK-CCMP][ESS],-93,2452,3155437667","Netcore_cfe215,30:fc:68:82:e9:5a,[WPA2-PSK-CCMP][WPS][ESS],-63,2467,259611665","PHICOMM_0f4275,0c:72:2c:39:ad:38,[WPA2-PSK-CCMP][ESS],-56,2437,472736212"]}