{"BSSID":"d0:26:39:fc:d5:90","IpAddress":"10.53.6.30","P2p0Mac":"23:77:4a:1a:39:13","SSID":"MERCURY_258738","androidId":"6827dad1cbed42a1","batteryLevel":30,"btAddress":"a3:40:a7:12:39:87","btName":"OPPO R7sm","buildAbi":"armeabi-v7a","buildAbi2":"armeabi","buildBoard":"MSM8916","buildBrand":"OPPO","buildCodename":"REL","buildDescription":"R7sm-user 7.1.2 NMF26Q 6cec739c release-keys","buildDevice":"R7sm","buildFingerprint":"OPPO/OPPO R7sm/R7sm:7.1.2/NMF26Q/6cec739c:user/release-keys","buildHardware":"qcom","buildHost":"qh-miui-ota-bd54","buildId":"NMF26Q","buildIncremental":"6cec739c","buildManufacturer":"OPPO","buildModel":"OPPO R7sm","buildName":"OPPO","buildProduct":"R7sm","buildRadioVersion":"dfucpphhqzztfhpql","buildRelease":"7.1.2","buildSdk":"25","buildSerialno":"7b14c240","buildTags":"release-keys","buildType":"user","buildUser":"MarkBuild","buildUtc":1501576411912,"cellScan":["61713,168900455","32818,9491","61731,26854","61731,38163","61731,14183"],"ci":168900455,"contacts":["奶奶,15202461869","姑妈,15301285363","外婆,15200927966","外公,13490163667","舅舅,18604695349","舅妈,18808037645","姨父,18701405582","姨娘,13503597287","亲爱的,13000805098","老弟,18704591250","老妹,13303468827","小明,15602854319","小李子,15503900850","巴渠瑛,15004326068","Leroy Brown,15904890133","陈韶延,13490428662","齐节如,15302291896","张颖辉,13900222969","Stacy Ward,13802510555","蒋红介,18001182727","贺瑜信,13902470495","王培,13902794135","Derek Hunter,13700292081","左辉佳,18801225307","李校,15805333957","倪峻演,13805453351","Diana Kelly,13702662809","喻宇孝,13605578637","包卫书,13702380892","吴团,13101030307","Stephanie Nichols,15508404004","张宏,13308305053","乌航琴,13503734226","余宏,13501988911","Vivian Wallace,13708025914","卡璎焱,15308071949","张河,15301776473","杨珊,13703361183","Jon Spencer,13602815057","程殊协,13806901198"],"cpuName":"Qualcomm Technologies, Inc MSM8939","densityDpi":560,"deviceId":"862989048592241","deviceSvn":"57","displayId":"R7sm-user 7.1.2 NMF26Q 6cec739c release-keys","extraInfo":"cmnet","height":0,"hidePkgs":[],"hmNotes":"","hookPkgs":[],"lac":61713,"latitude":30.8797314,"line1Number":"18224431183","longitude":104.2658489,"macAddress":"86:f8:eb:cb:d9:d5","memAvailable":937573392,"memFree":2812720178,"memTotal":3750293570,"mnc":"00","networkClass":1,"networkCountryIso":"cn","networkOperator":"46002","networkOperatorName":"中国移动","networkType":2,"networkTypeName":"EDGE","phoneType":1,"rgAndroid":"23","rgAreaode":"86","rgConNames":["上善若水","虞庞介"],"rgConsize":"2","rgCountry":"中国","rgDevice":"xiaomiRedmi 4X","rgIp":"139.207.57.247","rgLastLogin":1518364429214,"rgLocation":"四川省 电信","rgNetType":"切换飞行模式","rgOrPhone":"18224431183","rgPhoneNo":"18224431183","rgServer":"飞行模式切换","rgTime":1515046214718,"rgVcode":"玉米(发码)","rgVersion":"1.6.0","rgWxEmail":"未绑定","rgWxError":"","rgWxId":"wxid_sqfabu4kwf2s22","rgWxName":"虞庞介","rgWxNo":"未设置","rgWxPasswd":"Rmst@7890","rgWxQQ":"未绑定","rgWxStatus":"存活","rgWxWindows":"是","serialno":"7b14c240","simCountryIso":"cn","simOperator":"46002","simOperatorName":"中国移动","simSerialNumber":"8986022873404866580","simState":5,"subscriberId":"460022213529125","type":0,"typeName":"MOBILE","width":0,"wifiScan":["PHICOMM_204374,00:e0:4c:27:88:a0,[WPA-PSK-CCMP][WPA2-PSK-CCMP][WPS][ESS],-76,2462,220131603","MERCURY_a8cb7b,1c:60:de:1d:50:18,[WPA2-PSK-CCMP][ESS],-78,2462,1636836592","Netcore_031ed2,8c:f2:28:fe:1d:68,[WPA2-PSK-CCMP][WPS][ESS],-51,2462,2147432438","ChainaNet_3275,8c:21:0a:a5:3c:7e,[WPA2-PSK-CCMP][WPS][ESS],-83,2437,1293831379","Netcore_7a9dc9,38:46:08:3d:cd:5d,[WPA-PSK-CCMP][WPA2-PSK-CCMP][WPS][ESS],-80,2427,2341529668"]}