{"BSSID":"3c:18:25:5b:b9:e7","IpAddress":"10.71.8.67","P2p0Mac":"86:d3:5e:81:16:25","SSID":"Netcore_697bed","androidId":"0b65fff6ea0126f5","batteryLevel":57,"btAddress":"bc:45:67:e1:82:dc","btName":"HUAWEI HN3-T01","buildAbi":"armeabi-v7a","buildAbi2":"armeabi","buildBoard":"geefhd","buildBrand":"HUAWEI","buildCodename":"REL","buildDescription":"HUAWEI HN3-T01-user 6.0.1 MMB29T 10840b82 release-keys","buildDevice":"HUAWEI HN3-T01","buildFingerprint":"HUAWEI/HUAWEI HN3-T01/HUAWEI HN3-T01:6.0.1/MMB29T/10840b82:user/release-keys","buildHardware":"qcom","buildHost":"sp-ci-01-desktop","buildId":"MMB29T","buildIncremental":"10840b82","buildManufacturer":"HUAWEI","buildModel":"HUAWEI HN3-T01","buildName":"HUAWEI","buildProduct":"HUAWEI HN3-T01","buildRadioVersion":"dwmgbfrhuqnwget","buildRelease":"6.0.1","buildSdk":"23","buildSerialno":"1025c856","buildTags":"release-keys","buildType":"user","buildUser":"jenkins","buildUtc":1511699722023,"cellScan":["32771,41582","32771,1286","33028,117561376","32771,41584","32771,1541"],"ci":41584,"contacts":["奶奶,13808234827","姑妈,15207337422","外婆,14704811415","外公,18603255864","舅舅,15908835980","舅妈,13504852985","姨父,13307546755","姨娘,15704016132","亲爱的,15701622822","老弟,15900307872","老妹,13300591180","小明,15900665697","小李子,13500410781","祝瑛吾,18002707985","Gordon Gordon,18004966807","李培宫,15605900825","暴魄勋,13106003828","李惠灵,18005450281","Frank Mitchell,18006884549","娄仪荃,13300424685","霍彤熙,13706454248","李阁梧,13807221782","Sue Morales,13703878644","吴珂由,13490077388","张阁颂,18704132657","汪梦扬,15904623488","Cheryl Elliott,15001331180","彭印兴,15702980984","吴向耕,15906485963","陈雨阳,15105524108","Joshua Sullivan,15904037415","王校,13490831446","郗节童,18706960722","郎鹏康,13607488241","Alma Jenkins,13604247453","杨剑,15303361413","李乾,13800440389","杨河殊,13302944194","Bryan Murray,15301293304","张欣,14708252785","余孝,13702055212","景绣森,13005851898","Aaron Wallace,15602361904","王廉,13408418392"],"cpuName":"MT6582","densityDpi":240,"deviceId":"860165511887069","deviceSvn":"32","displayId":"HUAWEI HN3-T01-user 6.0.1 MMB29T 10840b82 release-keys","extraInfo":"3gwap","height":0,"hidePkgs":[],"hmNotes":"","hookPkgs":[],"lac":32771,"latitude":30.6448931,"line1Number":"18101916546","longitude":103.979312,"macAddress":"bb:18:df:c2:46:8f","memAvailable":4109836516,"memFree":12329509550,"memTotal":16439346066,"mnc":"03","networkClass":2,"networkCountryIso":"cn","networkOperator":"46003","networkOperatorName":"中国电信","networkType":5,"networkTypeName":"CDMA - EvDo rev. 0","phoneType":2,"rgAndroid":"23","rgAreaode":"86","rgConNames":["上善若水","时伊桐"],"rgConsize":"2","rgCountry":"中国","rgDevice":"xiaomiRedmi 4X","rgIp":"119.4.252.27","rgLastLogin":1518324685025,"rgLocation":"四川省成都市 联通","rgNetType":"切换飞行模式","rgOrPhone":"18101916546","rgPhoneNo":"18101916546","rgServer":"飞行模式切换","rgTime":1515313309435,"rgVcode":"尚一品(发码)","rgVersion":"1.6.0","rgWxEmail":"未绑定","rgWxError":"","rgWxId":"wxid_9vq8awgfhzw422","rgWxName":"时伊桐","rgWxNo":"未设置","rgWxPasswd":"Rmst@7890","rgWxQQ":"未绑定","rgWxStatus":"存活","rgWxWindows":"是","serialno":"1025c856","simCountryIso":"cn","simOperator":"46003","simOperatorName":"中国电信","simSerialNumber":"898530793061812401760","simState":5,"subscriberId":"460036616270509","type":0,"typeName":"MOBILE","width":0,"wifiScan":["PHICOMM_314864,e4:d3:32:44:13:bf,[WPA-PSK-CCMP][WPA2-PSK-CCMP][WPS][ESS],-61,2417,443852320","FAST_c0f21e,bc:d1:77:bd:5f:ee,[WPA-PSK-CCMP][WPA2-PSK-CCMP][WPS][ESS],-60,2412,3042833332","Tenda_486316,80:48:a5:fc:63:3a,[WPA2-PSK-CCMP][WPS][ESS],-76,2472,439029506","Netcore_8d5386,e8:4e:06:19:95:e1,[WPA-PSK-CCMP][WPA2-PSK-CCMP][WPS][ESS],-93,2462,1948729605","PHICOMM_bfe21e,9c:21:6a:09:b1:e2,[WPA-PSK-CCMP][WPA2-PSK-CCMP][ESS],-79,2422,737627261"]}