{"BSSID":"78:8a:04:1f:d3:a7","IpAddress":"192.168.12.179","P2p0Mac":"ab:51:9d:18:bc:4b","SSID":"Netcore_142fd2","androidId":"c793a0c217184174","batteryLevel":88,"btAddress":"d9:e1:f3:fd:73:a3","btName":"vivo X9","buildAbi":"armeabi-v7a","buildAbi2":"armeabi","buildBoard":"msm8996","buildBrand":"vivo","buildCodename":"REL","buildDescription":"PD1616-user 6.0.1 MMB29T 62958a58 release-keys","buildDevice":"PD1616","buildFingerprint":"vivo/vivo X9/PD1616:6.0.1/MMB29T/62958a58:user/release-keys","buildHardware":"qcom","buildHost":"mine","buildId":"MMB29T","buildIncremental":"62958a58","buildManufacturer":"vivo","buildModel":"vivo X9","buildName":"vivo","buildProduct":"PD1616","buildRadioVersion":"ygzurtojelmsmni","buildRelease":"6.0.1","buildSdk":"23","buildSerialno":"67124e37","buildTags":"release-keys","buildType":"user","buildUser":"Server","buildUtc":1497246650013,"cellScan":["33061,139765761","33024,2411","33024,98196097","33296,58352","33296,58154"],"ci":58154,"contacts":["奶奶,13505618035","姑妈,13805356414","外婆,15608672788","外公,13501531173","舅舅,13707007221","舅妈,18700860101","姨父,13708176698","姨娘,13302416646","亲爱的,18905657515","老弟,13100092395","老妹,18807273096","小明,15905976220","小李子,13300220776","慕容瑞诗,13703784887","Annie Burns,13705657677","张炬魄,15706107477","杨佑,18806976888","邢奇铜,18907274188","Danny Wright,13490500261","谈相念,13605573798","吴虎,13105676282","李怀,18900264050","Jacob Reyes,18002244037","任颂雷,15100703048","荣腾幸,15702621804","王愚宣,15902525511","Bernice King,15902982539","储乾吉,15004177569","姚梁律,13403288481","仲坚桂,15202886297","Lucille Harrison,13402948162","王苡,18903976926","罗森译,13008852743","李廉群,13202723925","David Sanchez,15603802636","蔡信锦,13905133319","王木璇,14707586006","暴孝炬,13803014426","Katherine Morris,13904172979","朱吾,15107957533","项启团,13105528150","杨祥贤,13005074016","Don Kelly,13101985770","于乾佳,14707191717","余吾,13903430919","金元军,13600079011","Audrey Reynolds,13504450428"],"cpuName":"Qualcomm Technologies, Inc MSM8953","densityDpi":320,"deviceId":"865223390757070","deviceSvn":"87","displayId":"PD1616-user 6.0.1 MMB29T 62958a58 release-keys","extraInfo":"Netcore_142fd2","height":0,"hidePkgs":[],"hmNotes":"","hookPkgs":[],"lac":33296,"latitude":30.7593513,"line1Number":"18224062606","longitude":104.2058666,"macAddress":"77:eb:6a:03:6f:00","memAvailable":611133250,"memFree":1222266500,"memTotal":1833399750,"mnc":"00","networkClass":1,"networkCountryIso":"cn","networkOperator":"46007","networkOperatorName":"中国移动","networkType":2,"networkTypeName":"EDGE","phoneType":1,"rgAndroid":"23","rgAreaode":"86","rgConNames":["上善若水","王龙"],"rgConsize":"2","rgCountry":"中国","rgDevice":"xiaomiRedmi 4X","rgIp":"119.4.252.221","rgLastLogin":1518335593333,"rgLocation":"四川省成都市 联通","rgNetType":"切换飞行模式","rgOrPhone":"18224062606","rgPhoneNo":"18224062606","rgServer":"飞行模式切换","rgTime":1515660788042,"rgVcode":"玉米(发码)","rgVersion":"1.6.0","rgWxEmail":"未绑定","rgWxError":"","rgWxId":"wxid_7t2qjhch158l22","rgWxName":"王龙","rgWxNo":"未设置","rgWxPasswd":"Rmst@7890","rgWxQQ":"未绑定","rgWxStatus":"存活","rgWxWindows":"是","serialno":"67124e37","simCountryIso":"cn","simOperator":"46007","simOperatorName":"中国移动","simSerialNumber":"8986025356973494880","simState":5,"subscriberId":"460077811078462","type":1,"typeName":"WIFI","width":0,"wifiScan":["PHICOMM_ff20dc,a8:57:4e:be:2c:60,[WPA-PSK-CCMP][WPA2-PSK-CCMP][WPS][ESS],-91,2437,376753020","MERCURY_9742,cc:34:29:19:36:2c,[WPA-PSK-CCMP][WPA2-PSK-CCMP][WPS][ESS],-54,2437,234710923","Tenda_eda9db,08:10:79:60:36:41,[WPA2-PSK-CCMP][WPS][ESS],-81,2412,3283736682","TP-LINK_d154,a8:57:4e:75:38:12,[WPA2-PSK-CCMP][ESS],-86,2437,388989520","MERCURY_41e316,08:10:79:7d:0e:bb,[WPA-PSK-CCMP][WPA2-PSK-CCMP][WPS][ESS],-90,2462,191591584"]}