{"BSSID":"5d:8d:17:a6:fa:97","IpAddress":"192.168.26.252","P2p0Mac":"d5:ae:81:96:d7:1c","SSID":"FAST_351687","androidId":"fa89dac03d6b9557","batteryLevel":74,"btAddress":"4c:31:43:92:9b:ec","btName":"ZTE G718C","buildAbi":"armeabi-v7a","buildAbi2":"armeabi","buildBoard":"bullhead","buildBrand":"ZTE","buildCodename":"REL","buildDescription":"ZTE-G718C-user 5.1.1 LMY48G ef8d85d3 release-keys","buildDevice":"ZTE-G718C","buildFingerprint":"ZTE/ZTE G718C/ZTE-G718C:5.1.1/LMY48G/ef8d85d3:user/release-keys","buildHardware":"qcom","buildHost":"wcc-miui-ota-bd25","buildId":"LMY48G","buildIncremental":"ef8d85d3","buildManufacturer":"ZTE","buildModel":"ZTE G718C","buildName":"ZTE","buildProduct":"ZTE-G718C","buildRadioVersion":"lkbmerdel","buildRelease":"5.1.1","buildSdk":"22","buildSerialno":"ccf736c8","buildTags":"release-keys","buildType":"user","buildUser":"android","buildUtc":1458920213066,"cellScan":[],"ci":0,"contacts":["奶奶,18601598572","姑妈,13101767512","外婆,18601518245","外公,13401697075","舅舅,15702376257","舅妈,18807537000","姨父,18801676833","姨娘,15308291035","亲爱的,15608027039","老弟,18905006034","老妹,18905822670","小明,18601622866","小李子,18008268341","杨良,18706592418","Frances Daniels,18701481044","皮隆鹄,15707186281","王湘瑞,18701587505","袁贺魄,13208836717","Rose Turner,13105938357","费棠铜,13490231894","杜孝演,13900227484","李伊儒,18708575403","Irene Grant,15708442080","于魄景,15100066971","方经蔚,15606795407","张相,13308433999","Carolyn Lee,15302250700","司徒嘉炯,15000942032","雷腾魄,15901226224","颜隆幸,13503525337","Jeanette Jackson,13507551193","孙权,13900593398","李桂,18904047557","鲁节毅,15703840232","Randall Rivera,18800515200","张孝,13903398874","司徒嵬畏,18701268926","於曜华,13204196294","Glen Boyd,13200080117","郝鹏添,15804205360","柏曜铁,15800442458","吴钰,18002982689","Christopher Hall,18001503436"],"cpuName":"Qualcomm MSM8926","densityDpi":480,"deviceId":"866714971166268","deviceSvn":"49","displayId":"ZTE-G718C-user 5.1.1 LMY48G ef8d85d3 release-keys","extraInfo":"FAST_351687","height":0,"hidePkgs":[],"hmNotes":"","hookPkgs":[],"lac":0,"latitude":30.7862318,"line1Number":"18328727647","longitude":104.2342012,"macAddress":"90:cb:6a:2a:b9:7f","memAvailable":32122086,"memFree":64244173,"memTotal":96366259,"mnc":"00","networkClass":2,"networkCountryIso":"cn","networkOperator":"46000","networkOperatorName":"中国移动","networkType":8,"networkTypeName":"HSDPA","phoneType":1,"rgAndroid":"23","rgAreaode":"86","rgConNames":["杭翔培","上善若水"],"rgConsize":"2","rgCountry":"中国","rgDevice":"xiaomiRedmi 4X","rgIp":"119.4.253.253","rgLastLogin":1518330442742,"rgLocation":"四川省成都市 联通","rgNetType":"切换飞行模式","rgOrPhone":"18328727647","rgPhoneNo":"18328727647","rgServer":"飞行模式切换","rgTime":1515408057757,"rgVcode":"玉米(发码)","rgVersion":"1.6.0","rgWxEmail":"未绑定","rgWxError":"","rgWxId":"wxid_hl7x56hhjhms22","rgWxName":"杭翔培","rgWxNo":"未设置","rgWxPasswd":"Rmst@7890","rgWxQQ":"未绑定","rgWxStatus":"存活","rgWxWindows":"是","serialno":"ccf736c8","simCountryIso":"cn","simOperator":"46000","simOperatorName":"中国移动","simSerialNumber":"8986022469601197175","simState":5,"subscriberId":"460004661337444","type":1,"typeName":"WIFI","width":0,"wifiScan":["MERCURY_aebfcb,be:f9:a5:b0:38:69,[WPA-PSK-CCMP][WPA2-PSK-CCMP][WPS][ESS],-87,2472,403427685","Netcore_105874,fe:e6:9a:21:32:9d,[WPA2-PSK-CCMP][ESS],-52,2462,2014027923","FAST_8cbf31,18:21:0f:b8:5a:c3,[WPA2-PSK-CCMP][WPS][ESS],-60,2412,431368625","PHICOMM_21530f,36:d5:6f:ca:58:4d,[WPA-PSK-CCMP][WPA2-PSK-CCMP][WPS][ESS],-87,2437,3006728869","FAST_1647,86:3f:ba:13:95:36,[WPA-PSK-CCMP][WPA2-PSK-CCMP][WPS][ESS],-92,2412,200314378","MERCURY_bfe154,d0:8d:ef:03:2c:19,[WPA-PSK-CCMP][WPA2-PSK-CCMP][ESS],-52,2412,372131454"]}