{"BSSID":"d6:40:67:35:aa:21","IpAddress":"10.7.89.94","P2p0Mac":"bd:41:a6:2a:2e:77","SSID":"FAST_848bae","androidId":"e6d77dbb160c2da2","batteryLevel":65,"btAddress":"56:02:43:7b:69:93","btName":"Redmi Note 2","buildAbi":"armeabi-v7a","buildAbi2":"armeabi","buildBoard":"MSM8960","buildBrand":"Xiaomi","buildCodename":"REL","buildDescription":"hermes-user 5.0 LRX21M 1767c828 release-keys","buildDevice":"hermes","buildFingerprint":"Xiaomi/Redmi Note 2/hermes:5.0/LRX21M/1767c828:user/release-keys","buildHardware":"qcom","buildHost":"bs189","buildId":"LRX21M","buildIncremental":"1767c828","buildManufacturer":"Xiaomi","buildModel":"Redmi Note 2","buildName":"Xiaomi","buildProduct":"hermes","buildRadioVersion":"motdfjjeudquxvf","buildRelease":"5.0","buildSdk":"21","buildSerialno":"fc73d6ce","buildTags":"release-keys","buildType":"user","buildUser":"MarkBuild","buildUtc":1501336836531,"cellScan":[],"ci":0,"contacts":["奶奶,13701501321","姑妈,13705078217","外婆,18604993668","外公,13007732526","舅舅,15607867741","舅妈,15706090641","姨父,13007536007","姨娘,15906107639","亲爱的,15006253240","老弟,15706466528","老妹,13505391535","小明,13907983338","小李子,18806237964","甄寿镜,15101663201","Pedro Stewart,15100038052","范洋铭,13205704126","窦佳洋,15903064744","吴影,15100498701","Jesse Stephens,15005947942","舒铁京,15808357116","施祥森,13007845033","陈商相,18908581629","Jacob Elliott,15308225163","王宫,18606724317","娄佑盈,15301764882","杨鑫薇,14703774183","Lynn Knight,18800046002","吴寿,13307402181","余思,13201188675","廉剑祥,18704994817","Holly Gray,18805165104","王如胤,18902148409","杨湘,13901274428","伏英翰,13000364066","Joe Clark,13002992117","张行游,13803767875","骆佩薇,18901558334","计勋琴,13103511212","Arthur Rose,13107037567","龚举况,13700363153","储君甲,13700423264","萧渠雄,15200574325","Calvin Bailey,15208418970","茅卫杭,15205200031"],"cpuName":"MT6795","densityDpi":560,"deviceId":"867311197432050","deviceSvn":"72","displayId":"hermes-user 5.0 LRX21M 1767c828 release-keys","extraInfo":"cmwap","height":0,"hidePkgs":[],"hmNotes":"","hookPkgs":[],"lac":0,"latitude":30.7606845,"line1Number":"15198147331","longitude":104.3185082,"macAddress":"14:6d:f2:84:b8:8d","memAvailable":172055312,"memFree":344110625,"memTotal":516165937,"mnc":"00","networkClass":2,"networkCountryIso":"cn","networkOperator":"46002","networkOperatorName":"中国移动","networkType":8,"networkTypeName":"HSDPA","phoneType":1,"rgAndroid":"23","rgAreaode":"86","rgConNames":["上善若水","于炯莉"],"rgConsize":"2","rgCountry":"中国","rgDevice":"xiaomiRedmi 4X","rgIp":"119.4.254.136","rgLastLogin":1518379630038,"rgLocation":"四川省成都市 联通","rgNetType":"切换飞行模式","rgOrPhone":"15198147331","rgPhoneNo":"15198147331","rgServer":"飞行模式切换","rgTime":1516004776265,"rgVcode":"玉米(发码)","rgVersion":"1.6.3","rgWxEmail":"未绑定","rgWxError":"","rgWxId":"wxid_owzsx2nyd92c22","rgWxName":"于炯莉","rgWxNo":"未设置","rgWxPasswd":"Rmst@7890","rgWxQQ":"未绑定","rgWxStatus":"存活","rgWxWindows":"否","serialno":"fc73d6ce","simCountryIso":"cn","simOperator":"46002","simOperatorName":"中国移动","simSerialNumber":"8986023538912730615","simState":5,"subscriberId":"460022914792454","type":0,"typeName":"MOBILE","width":0,"wifiScan":["FAST_140537,d5:ed:a6:6d:60:61,[WPA-PSK-CCMP][WPA2-PSK-CCMP][WPS][ESS],-78,2412,2578626547","TP-LINK_c0e31d,73:6c:ad:eb:30:f2,[WPA2-PSK-CCMP][ESS],-82,2437,229738167","TP-LINK_8427,f5:12:63:ab:5c:ae,[WPA2-PSK-CCMP][WPS][ESS],-92,2462,2018832163","TP-LINK_97ca,41:4a:b0:2a:9c:a6,[WPA2-PSK-CCMP][WPS][ESS],-54,2412,3615426583","MERCURY_25497c,63:e9:7f:11:73:5b,[WPA2-PSK-CCMP][WPS][ESS],-72,2412,398790587","Tenda_9ed1eb,5b:ac:9c:b3:5f:36,[WPA2-PSK-CCMP][ESS],-81,2412,784029886","TP-LINK_6515,ab:73:23:dd:c0:11,[WPA-PSK-CCMP][WPA2-PSK-CCMP][WPS][ESS],-92,2437,506528794"]}