{"BSSID":"9d:b4:fe:89:05:13","IpAddress":"10.76.82.227","P2p0Mac":"59:03:f0:0b:d3:79","SSID":"Netcore_a9dbf8","androidId":"33a5beda5e0d2142","batteryLevel":70,"btAddress":"31:21:5d:59:3f:88","btName":"MIX 2","buildAbi":"armeabi-v7a","buildAbi2":"armeabi","buildBoard":"ventana","buildBrand":"Xiaomi","buildCodename":"REL","buildDescription":"chiron-user 7.1.2 NMF26Q 3a9154f1 release-keys","buildDevice":"chiron","buildFingerprint":"Xiaomi/MIX 2/chiron:7.1.2/NMF26Q/3a9154f1:user/release-keys","buildHardware":"qcom","buildHost":"LGEACI2R5","buildId":"NMF26Q","buildIncremental":"3a9154f1","buildManufacturer":"Xiaomi","buildModel":"MIX 2","buildName":"Xiaomi","buildProduct":"chiron","buildRadioVersion":"rdjecoikcwiqpna","buildRelease":"7.1.2","buildSdk":"25","buildSerialno":"3ef58a4e","buildTags":"release-keys","buildType":"user","buildUser":"android","buildUtc":1497302967241,"cellScan":[],"ci":0,"contacts":["奶奶,18703002128","姑妈,13206056734","外婆,13501572537","外公,15507628151","舅舅,13490490301","舅妈,15805996753","姨父,18003933289","姨娘,15100596689","亲爱的,15506335066","老弟,13003335707","老妹,14703605290","小明,13407406912","小李子,13490162009","于韶恒,13505613803","Roberto Torres,13804925353","糜声惠,18904630743","糜骥恺,15305034539","夏翰郡,14701560285","Joseph Hamilton,14702063459","刘甲佳,15905848073","张岁,13107407868","祁儒阁,15507347568","Brittany Stevens,18605983657","洪迅逵,15303545189","陈默,13006669036","王艺,13904311726","Barbara Ray,13803293308","杨祥,13406000300","鲁幸海,13802562141","杨倩,18607542199","Florence Ortiz,13106884873","吴生,15803390771","李琴,13702501340","陈先驹,18704044837","Jacqueline Washington,18808592768","潘游汉,18705992692","龙夏玉,15700907419","王为,13907156974","Zachary Ramirez,13801630334","陈璇筱,15307180865","柳朔同,18605011033","孙贤虎,15101105564","Shannon Porter,15100774572","陈吾微,15808122567","于烁琴,13490142638","乌京乾,13906225013","Curtis Ruiz,13601964856","巫兴卿,15107350987"],"cpuName":"Qualcomm Technologies, Inc MSM8998","densityDpi":560,"deviceId":"862784488691342","deviceSvn":"89","displayId":"chiron-user 7.1.2 NMF26Q 3a9154f1 release-keys","extraInfo":"cmnet","height":0,"hidePkgs":[],"hmNotes":"","hookPkgs":[],"lac":0,"latitude":30.440782,"line1Number":"18224442024","longitude":103.9018437,"macAddress":"70:ea:03:d8:ad:44","memAvailable":701634028,"memFree":2104902084,"memTotal":2806536112,"mnc":"00","networkClass":1,"networkCountryIso":"cn","networkOperator":"46000","networkOperatorName":"中国移动","networkType":2,"networkTypeName":"EDGE","phoneType":1,"rgAndroid":"23","rgAreaode":"86","rgConNames":["上善若水","王君"],"rgConsize":"2","rgCountry":"中国","rgDevice":"xiaomiRedmi 4X","rgIp":"119.4.254.186","rgLastLogin":1518348725362,"rgLocation":"四川省成都市 联通","rgNetType":"切换飞行模式","rgOrPhone":"18224442024","rgPhoneNo":"18224442024","rgServer":"飞行模式切换","rgTime":1515226233449,"rgVcode":"玉米(发码)","rgVersion":"1.6.0","rgWxEmail":"未绑定","rgWxError":"","rgWxId":"wxid_0fc2oyj4rglj22","rgWxName":"王君","rgWxNo":"未设置","rgWxPasswd":"Rmst@7890","rgWxQQ":"未绑定","rgWxStatus":"存活","rgWxWindows":"是","serialno":"3ef58a4e","simCountryIso":"cn","simOperator":"46000","simOperatorName":"中国移动","simSerialNumber":"8986002607357727144","simState":5,"subscriberId":"460008021031719","type":0,"typeName":"MOBILE","width":0,"wifiScan":["TP-LINK_58ca,fd:ee:0b:b8:25:87,[WPA2-PSK-CCMP][WPS][ESS],-87,2412,2559733763","MERCURY_7b87a9,30:96:ed:6a:8e:c9,[WPA-PSK-CCMP][WPA2-PSK-CCMP][WPS][ESS],-63,2462,741231539","MERCURY_f42fd0,a0:a2:de:8b:34:66,[WPA2-PSK-CCMP][WPS][ESS],-84,2447,358533375","Netcore_5265a6,75:5e:05:60:1e:65,[WPA-PSK-CCMP][WPA2-PSK-CCMP][ESS],-78,2412,221699548","Netcore_97427a,32:7a:91:53:e5:14,[WPA2-PSK-CCMP][WPS][ESS],-92,2412,492335524","ChainaNet_d8dc,68:f5:87:23:4e:49,[WPA-PSK-CCMP][WPA2-PSK-CCMP][WPS][ESS],-85,2462,3454229248","PHICOMM_8bafd9,2f:82:7a:dc:ed:55,[WPA-PSK-CCMP][WPA2-PSK-CCMP][ESS],-79,2437,305306254","Netcore_0fcbfc,1d:99:23:24:a2:fa,[WPA-PSK-CCMP][WPA2-PSK-CCMP][ESS],-56,2412,501050218"]}